advenced_logger.py
advenced_logger-0.1.1.dist-info/METADATA
advenced_logger-0.1.1.dist-info/WHEEL
advenced_logger-0.1.1.dist-info/top_level.txt
advenced_logger-0.1.1.dist-info/RECORD
