Metadata-Version: 2.1
Name: advenced-logger
Version: 0.1.1
Summary: Advanced logging configuration with support for multi-threading and multi-processing.Provides structured logging, context management, and automatic rotation.
Author: Zongwei Du
Author-email: pxwtp6519@gmail.com
Classifier: Programming Language :: Python :: 3
Classifier: License :: OSI Approved :: MIT License
Classifier: Operating System :: OS Independent
Requires-Python: >=3.6
Requires-Dist: loguru
